kunnai/expand_columns.py
kunnai/pandas_json.py
kunnai/parameter_checks.py
kunnai-0.1.2.dist-info/LICENSE
kunnai-0.1.2.dist-info/METADATA
kunnai-0.1.2.dist-info/WHEEL
kunnai-0.1.2.dist-info/RECORD
