Metadata-Version: 2.3
Name: kunnai
Version: 0.1.2
Summary: Library to facilitate working with Pandas and REST APIs.
License: Apache-2.0
Author: lucas
Author-email: lucas.jamar@carpentrix.com
Requires-Python: >=3.10
Classifier: License :: OSI Approved :: Apache Software License
Classifier: Programming Language :: Python :: 3
Classifier: Programming Language :: Python :: 3.10
Classifier: Programming Language :: Python :: 3.11
Classifier: Programming Language :: Python :: 3.12
Classifier: Programming Language :: Python :: 3.13
Requires-Dist: pandas (>=2.2.3,<3.0.0)
Requires-Dist: pandera (>=0.22.1,<0.23.0)
Requires-Dist: pydantic (>=2.10.5,<3.0.0)
Requires-Dist: pydantic-extra-types (>=2.10.1,<3.0.0)
Project-URL: Documentation, https://github.com/lucasjamar/kunnai
Project-URL: Homepage, https://github.com/lucasjamar/kunnai
Project-URL: Repository, https://github.com/lucasjamar/kunnai
